<Properties StartupConfiguration="{0B965200-0CDD-42A9-B97F-DAB01229DA07}|Default">
  <MultiItemStartupConfigurations />
  <MonoDevelop.Ide.Workbench ActiveDocument="Program.cs">
    <Files>
      <File FileName="Program.cs" Line="7" Column="1" />
    </Files>
    <Pads>
      <Pad Id="ProjectPad">
        <State name="__root__">
          <Node name="Web" expanded="True">
            <Node name="Web" expanded="True">
              <Node name="Program.cs" selected="True" />
            </Node>
          </Node>
        </State>
      </Pad>
      <Pad Id="MonoDevelop.Debugger.WatchPad">
        <State />
      </Pad>
    </Pads>
  </MonoDevelop.Ide.Workbench>
  <MonoDevelop.Ide.DebuggingService.Breakpoints>
    <BreakpointStore />
  </MonoDevelop.Ide.DebuggingService.Breakpoints>
  <MonoDevelop.Ide.DebuggingService.PinnedWatches />
  <MonoDevelop.Ide.ItemProperties.Web PreferredExecutionTarget="/Applications/Google Chrome.app" />
  <MonoDevelop.Ide.Workspace ActiveConfiguration="Debug" />
</Properties>